<?xml version="1.1"?>
<map proto="1.4">
<name>Winter Wakening</name>
<version>1.1.0</version>
<objective>The team who first captures the other team's wools, located in the opposite wool rooms, wins!</objective>
<authors>
    <author uuid="fe3608b7-d105-4029-8800-34b3147065b6"/>
<!-- rockymine -->
    <author uuid="dff980ed-9f69-491e-b79c-30c21350baf2"/>
<!-- DoomRobotBoy -->
</authors>
<teams>
    <team color="blue" max="32" max-overfill="36">Blue Team</team>
    <team color="dark red" max="32" max-overfill="36">Red Team</team>
</teams>
<spawns>
    <spawns>
        <spawn team="red" kit="red">
            <regions yaw="90">
                <cylinder base="-375.5,10,-149.5" radius="1" height="0"/>
            </regions>
        </spawn>
        <spawn team="blue" kit="blue">
            <regions yaw="-90">
                <cylinder base="-699.5,10,-149.5" radius="1" height="0"/>
            </regions>
        </spawn>
    </spawns>
    <default>
        <regions yaw="90">
            <cylinder base="-537.5,41,-149.5" radius="1" height="0"/>
        </regions>
    </default>
</spawns>
<kits>
    <kit name="spawn">
        <item slot="0">iron sword</item>
        <item slot="1" enchantment="arrow infinite:1;arrow damage:1">bow</item>
        <item slot="28">arrow</item>
        <item slot="2" enchantment="dig speed:1">iron pickaxe</item>
        <item slot="3" enchantment="dig speed:1">iron axe</item>
        <item slot="4" amount="32" damage="1">log_2</item>
        <item slot="5" amount="64">glass</item>
        <item slot="32" amount="64">glass</item>
        <item slot="6" amount="16">snow ball</item>
        <item slot="7" amount="64">golden apple</item>
        <item slot="8" amount="32">cooked beef</item>
        <item slot="9" attributes="generic.movementSpeed:add:-1">shears</item>
    </kit>
    <kit name="red" parents="spawn">
        <chestplate color="993333" damage="-3000">leather chestplate</chestplate>
    </kit>
    <kit name="blue" parents="spawn">
        <chestplate color="334CB2" damage="-3000">leather chestplate</chestplate>
    </kit>
</kits>
<filters>
    <filter name="no-void">
        <not>
            <void/>
        </not>
    </filter>
    <filter name="only-cobweb">
        <block>web</block>
    </filter>
    <filter name="only-leaves">
        <block>leaves_2</block>
    </filter>
    <filter name="only-red">
        <allow>
            <team>Red Team</team>
        </allow>
    </filter>
    <filter name="only-blue">
        <allow>
            <team>Blue Team</team>
        </allow>
    </filter>
</filters>
<regions>
    <rectangle name="red-spawn" min="-368,-180" max="-401,-119"/>
    <rectangle name="blue-spawn" min="-707,-119" max="-674,-180"/>
    <circle name="pink-wool" base="-658.5,-86.5" radius="9"/>
    <circle name="magenta-wool" base="-658.5,-212.5" radius="9"/>
    <circle name="green-wool" base="-416.5,-212.5" radius="9"/>
    <circle name="lime-wool" base="-416.5,-86.5" radius="9"/>
    <rectangle name="map" min="oo,oo" max="-oo,-oo"/>
    <rectangle name="void-gap" min="-576,-120" max="-499,-179"/>
    <rectangle name="water-void-gap" min="-553,-142" max="522,158"/>
    <apply enter="only-red" message="Only Red Team may enter here!">
        <region name="red-spawn"/>
        <region name="pink-wool"/>
        <region name="magenta-wool"/>
    </apply>
    <apply enter="only-blue" message="Only Blue Team may enter here!">
        <region name="blue-spawn"/>
        <region name="green-wool"/>
        <region name="lime-wool"/>
    </apply>
    <apply block="only-cobweb" message="You may only destroy cobwebs in/around the Wool Room!">
        <region name="pink-wool"/>
        <region name="magenta-wool"/>
        <region name="green-wool"/>
        <region name="lime-wool"/>
    </apply>
    <apply block="deny-all" message="You may not modify the spawns!">
        <region name="red-spawn"/>
        <region name="blue-spawn"/>
    </apply>
    <apply block="only-leaves" message="You may only build with leaves above the water in the center.">
        <region name="water-void-gap"/>
    </apply>
    <apply block="no-void" message="You may not edit the void area!">
        <complement>
            <region name="map"/>
            <region name="void-gap"/>
        </complement>
    </apply>
</regions>
<toolrepair>
    <tool>iron sword</tool>
    <tool>bow</tool>
    <tool>iron pickaxe</tool>
    <tool>iron axe</tool>
</toolrepair>
<itemremove>
    <item>arrow</item>
    <item>leather chestplate</item>
    <item>log_2</item>
    <item>cooked beef</item>
    <item>golden apple</item>
    <item>string</item>
</itemremove>
<maxbuildheight>30</maxbuildheight>
<wools>
    <wool team="red" color="magenta" location="0,0,0">
        <monument><block>-385.5,11,-152.5</block></monument>
    </wool>
    <wool team="red" color="pink" location="0,0,0">
        <monument><block>-385.5,11,-146.5</block></monument>
    </wool>
    <wool team="blue" color="green" location="0,0,0">
        <monument><block>689.5,11,-152.5</block></monument>
    </wool>
    <wool team="blue" color="lime" location="0,0,0">
        <monument><block>-689.5,11,-146.5</block></monument>
    </wool>
</wools>
</map>
